polywrap/__init__.py
polywrap/py.typed
polywrap-0.1.2.dist-info/METADATA
polywrap-0.1.2.dist-info/WHEEL
polywrap-0.1.2.dist-info/RECORD
