Metadata-Version: 2.1
Name: polywrap
Version: 0.1.2
Summary: Polywrap Python SDK
Author: Cesar
Author-email: cesar@polywrap.io
Requires-Python: >=3.10,<4.0
Classifier: Programming Language :: Python :: 3
Classifier: Programming Language :: Python :: 3.10
Classifier: Programming Language :: Python :: 3.11
Requires-Dist: polywrap-client (==0.1.2)
Requires-Dist: polywrap-client-config-builder (==0.1.2)
Requires-Dist: polywrap-core (==0.1.2)
Requires-Dist: polywrap-ethereum-wallet (==0.1.2)
Requires-Dist: polywrap-fs-plugin (==0.1.2)
Requires-Dist: polywrap-http-plugin (==0.1.2)
Requires-Dist: polywrap-manifest (==0.1.2)
Requires-Dist: polywrap-msgpack (==0.1.2)
Requires-Dist: polywrap-plugin (==0.1.2)
Requires-Dist: polywrap-sys-config-bundle (==0.1.2)
Requires-Dist: polywrap-uri-resolvers (==0.1.2)
Requires-Dist: polywrap-wasm (==0.1.2)
Requires-Dist: polywrap-web3-config-bundle (==0.1.2)
